aphelper/__init__.py
aphelper/core.py
aphelper/enums.py
aphelper-0.0.6.dist-info/LICENSE
aphelper-0.0.6.dist-info/METADATA
aphelper-0.0.6.dist-info/WHEEL
aphelper-0.0.6.dist-info/top_level.txt
aphelper-0.0.6.dist-info/RECORD
