Metadata-Version: 2.1
Name: aphelper
Version: 0.0.6
Summary: A Python package to enable declarative definition of argparse CLIs
Home-page: https://github.com/jfcarter2358/aphelper
Author: John Carter
Author-email: jfcarter2358@gmail.com
License: MIT
Platform: UNKNOWN
Requires-Python: >=3.7
